tercuz.py
TerCuz-1.10.dist-info/METADATA
TerCuz-1.10.dist-info/WHEEL
TerCuz-1.10.dist-info/top_level.txt
TerCuz-1.10.dist-info/RECORD
