Metadata-Version: 2.1
Name: TerCuz
Version: 1.10
Summary: Advance Terminal Customizer
Author-email: Clarence Parmar <git.clarence@gmail.com>
Project-URL: Homepage, https://github.com/clarenceparmar/TerCuz
Classifier: Programming Language :: Python :: 3
Classifier: License :: OSI Approved :: MIT License
Classifier: Operating System :: OS Independent
Requires-Python: >=3.7
